README.rst
setup.py
amanwa32/__init__.py
amanwa32/decorators.py
amanwa32/exceptions.py
amanwa32/handlers.py
amanwa32/middleware.py
amanwa32/response.py
amanwa32/router.py
amanwa32/router_test.py
amanwa32.egg-info/PKG-INFO
amanwa32.egg-info/SOURCES.txt
amanwa32.egg-info/dependency_links.txt
amanwa32.egg-info/not-zip-safe
amanwa32.egg-info/requires.txt
amanwa32.egg-info/top_level.txt
amanwa32_extras/__init__.py
amanwa32_extras/auth.py
amanwa32_extras/authomatic_adapter.py
amanwa32_extras/dal.py
amanwa32_extras/dal_test.py
amanwa32_extras/i18n.py
amanwa32_extras/jinja2.py
amanwa32_extras/json1.py
amanwa32_extras/junk.py
amanwa32_extras/local.py
amanwa32_extras/mako.py
amanwa32_extras/routes.py
amanwa32_extras/securecookie.py
amanwa32_extras/security.py
amanwa32_extras/sessions.py
amanwa32_extras/user.py
amanwa32_extras/user_test.py
amanwa32_extras/xsrf.py