Metadata-Version: 2.1
Name: amanwa32
Version: 1.0.9
Summary: testing wa3 custom
Home-page: UNKNOWN
Author: a
Author-email: angrish_aman@yahoo.com
License: Apache Software License
Platform: any
Provides-Extra: extras
